dramamoyu/__init__.py
dramamoyu/cli.py
dramamoyu/modules/__init__.py
dramamoyu/modules/ai/__init__.py
dramamoyu/modules/ai/engine.py
dramamoyu/modules/ai/plugins.py
dramamoyu/modules/providers/__init__.py
dramamoyu/modules/providers/baidu.py
dramamoyu/modules/providers/base.py
dramamoyu/modules/providers/hema.py
dramamoyu/modules/providers/honggguo.py
dramamoyu/modules/providers/qimao.py
dramamoyu/modules/providers/weiguan.py
dramamoyu/modules/utils/__init__.py
dramamoyu/modules/utils/models.py
dramamoyu/modules/utils/player.py
dramamoyu/modules/utils/store.py
freegpthub_dramamoyu-0.1.1.dist-info/METADATA
freegpthub_dramamoyu-0.1.1.dist-info/WHEEL
freegpthub_dramamoyu-0.1.1.dist-info/entry_points.txt
freegpthub_dramamoyu-0.1.1.dist-info/top_level.txt
freegpthub_dramamoyu-0.1.1.dist-info/zip-safe
freegpthub_dramamoyu-0.1.1.dist-info/RECORD
