Metadata-Version: 2.1
Name: freegpthub-dramamoyu
Version: 0.1.1
Summary: DramaMoyu: Your go-to terminal app for watching short dramas while "working".
Home-page: https://github.com/CharlesPikachu/FreeGPTHub/tree/main/playground/dramamoyu
Author: Zhenchao Jin
Author-email: charlesblwx@gmail.com
License: Apache License 2.0
Classifier: License :: OSI Approved :: Apache Software License
Classifier: Programming Language :: Python :: 3
Classifier: Intended Audience :: Developers
Classifier: Operating System :: OS Independent
Requires-Dist: requests
Requires-Dist: freegpthub
Requires-Dist: rich
Requires-Dist: tqdm
